pegol/__init__.py
pegol/main.py
pegol-0.3.0.dist-info/entry_points.txt
pegol-0.3.0.dist-info/licenses/LICENSE
pegol-0.3.0.dist-info/WHEEL
pegol-0.3.0.dist-info/METADATA
pegol-0.3.0.dist-info/RECORD
