Metadata-Version: 2.4
Name: pegol
Version: 0.3.0
Summary: Fun interactive congratulation animation with hearts using curses.
Keywords: fun,animation,hearts,curses
Author-email: Pegol Reda Shokry <sosoreda481@gmail.com>
Requires-Python: >=3.10
Classifier: Programming Language :: Python :: 3
Classifier: License :: OSI Approved :: MIT License
Classifier: Operating System :: OS Independent
License-File: LICENSE
